licensecheck/__init__.py
licensecheck/__main__.py
licensecheck/checker.py
licensecheck/cli.py
licensecheck/fmt.py
licensecheck/html.template
licensecheck/packageinfo.py
licensecheck/session.py
licensecheck/types.py
licensecheck/license_matrix/__init__.py
licensecheck/license_matrix/matrix.csv
licensecheck/license_matrix/spdx.py
licensecheck/pypi_licenses/osi_approved.txt
licensecheck/pypi_licenses/other.txt
licensecheck/resolvers/__init__.py
licensecheck/resolvers/native.py
licensecheck/resolvers/uv.py
licensecheck-2025.0.1.dist-info/METADATA
licensecheck-2025.0.1.dist-info/WHEEL
licensecheck-2025.0.1.dist-info/entry_points.txt
licensecheck-2025.0.1.dist-info/licenses/LICENSE.md
licensecheck-2025.0.1.dist-info/RECORD
