Metadata-Version: 2.4
Name: licensecheck
Version: 2025.0.1
Summary: Output the licenses used by dependencies and check if these are compatible with the project license
Project-URL: Homepage, https://github.com/FHPythonUtils/LicenseCheck
Project-URL: Repository, https://github.com/FHPythonUtils/LicenseCheck
Project-URL: Documentation, https://github.com/FHPythonUtils/LicenseCheck/blob/master/README.md
Author: FredHappyface
License-Expression: MIT
License-File: LICENSE.md
Classifier: Development Status :: 5 - Production/Stable
Classifier: Environment :: Console
Classifier: Environment :: MacOS X
Classifier: Environment :: Win32 (MS Windows)
Classifier: Intended Audience :: Developers
Classifier: Intended Audience :: Education
Classifier: Natural Language :: English
Classifier: Operating System :: OS Independent
Classifier: Programming Language :: Python :: Implementation :: CPython
Classifier: Topic :: Security
Classifier: Topic :: Software Development :: Libraries :: Python Modules
Classifier: Topic :: Utilities
Requires-Python: >=3.9
Requires-Dist: appdirs>=1.4.4
Requires-Dist: fhconfparser>=2024.1
Requires-Dist: license-expression>=30.4.1
Requires-Dist: loguru>=0.7.3
Requires-Dist: markdown>=3.7
Requires-Dist: packaging>=24.2
Requires-Dist: requests-cache>=1.2.1
Requires-Dist: requests>=2.32.3
Requires-Dist: requirements-parser>=0.11.0
Requires-Dist: rich>=13.9.4
Requires-Dist: tomli>=2.2.1
Requires-Dist: uv>=0.6.6
